taxburst/__init__.py
taxburst/__main__.py
taxburst/checks.py
taxburst/output.py
taxburst/parsers.py
taxburst/tree_utils.py
taxburst/templates/krona-footer.html
taxburst/templates/krona-header.html
taxburst/templates/krona.html
taxburst-0.3.1.dist-info/licenses/LICENSE.txt
taxburst-0.3.1.dist-info/METADATA
taxburst-0.3.1.dist-info/WHEEL
taxburst-0.3.1.dist-info/entry_points.txt
taxburst-0.3.1.dist-info/top_level.txt
taxburst-0.3.1.dist-info/RECORD
