Metadata-Version: 2.4
Name: taxburst
Version: 0.3.1
Summary: sunburst plots for taxonomy
Author-email: Titus Brown <titus@idyll.org>
Requires-Python: >=3.11
License-File: LICENSE.txt
Requires-Dist: pytest<9,>=8.3.4
Requires-Dist: jinja2<4,>=3.1.2
Dynamic: license-file
